{
  "generatedAt": "2025-08-19T04:41:49.751Z",
  "sourceDatabase": "voter_database_muhsin_fixed.json",
  "totalVotersProcessed": 39789,
  "unassignedVoters": 0,
  "totalHalls": 18,
  "halls": [
    {
      "hallName": "বেগম রোকেয়া হল",
      "englishName": "Begum_Rokeya_Hall",
      "filename": "./hall_databases/Begum_Rokeya_Hall.json",
      "totalVoters": 5643,
      "prefix": "রক",
      "totalDepartments": 93
    },
    {
      "hallName": "কবি সুফিয়া কামাল হল",
      "englishName": "Kabi_Sufia_Kamal_Hall",
      "filename": "./hall_databases/Kabi_Sufia_Kamal_Hall.json",
      "totalVoters": 4434,
      "prefix": "সক",
      "totalDepartments": 88
    },
    {
      "hallName": "শামসুন নাহার হল",
      "englishName": "Shamsun_Nahar_Hall",
      "filename": "./hall_databases/Shamsun_Nahar_Hall.json",
      "totalVoters": 4090,
      "prefix": "শন",
      "totalDepartments": 90
    },
    {
      "hallName": "বঙ্গমাতা শেখ ফজিলাতুন্নেছা মুজিব হল",
      "englishName": "Begum_Fazilatunnesa_Mujib_Hall",
      "filename": "./hall_databases/Begum_Fazilatunnesa_Mujib_Hall.json",
      "totalVoters": 2641,
      "prefix": "ফম",
      "totalDepartments": 69
    },
    {
      "hallName": "জগন্নাথ হল",
      "englishName": "Jagannath_Hall",
      "filename": "./hall_databases/Jagannath_Hall.json",
      "totalVoters": 2222,
      "prefix": "জগ",
      "totalDepartments": 87
    },
    {
      "hallName": "বাংলাদেশ-কুয়েত মৈত্রী হল",
      "englishName": "Bangladesh_Kuwait_Maitree_Hall",
      "filename": "./hall_databases/Bangladesh_Kuwait_Maitree_Hall.json",
      "totalVoters": 2105,
      "prefix": "কম",
      "totalDepartments": 59
    },
    {
      "hallName": "বিজয় একাত্তর হল",
      "englishName": "Bijoy_Ekattor_Hall",
      "filename": "./hall_databases/Bijoy_Ekattor_Hall.json",
      "totalVoters": 2040,
      "prefix": "বএ",
      "totalDepartments": 64
    },
    {
      "hallName": "ড. মুহম্মদ শহীদুল্লাহ হল",
      "englishName": "Dr_Muhammad_Shahidullah_Hall",
      "filename": "./hall_databases/Dr_Muhammad_Shahidullah_Hall.json",
      "totalVoters": 1998,
      "prefix": "শহ",
      "totalDepartments": 31
    },
    {
      "hallName": "শহীদ সার্জেন্ট জহুরুল হক হল",
      "englishName": "Shaheed_Sergeant_Zahurul_Haq_Hall",
      "filename": "./hall_databases/Shaheed_Sergeant_Zahurul_Haq_Hall.json",
      "totalVoters": 1960,
      "prefix": "জহ",
      "totalDepartments": 60
    },
    {
      "hallName": "ফজলুল হক মুসলিম হল",
      "englishName": "Fazlul_Huq_Muslim_Hall",
      "filename": "./hall_databases/Fazlul_Huq_Muslim_Hall.json",
      "totalVoters": 1762,
      "prefix": "ফহ",
      "totalDepartments": 32
    },
    {
      "hallName": "মুক্তিযোদ্ধা জিয়াউর রহমান হল",
      "englishName": "Muktijoddha_Ziaur_Rahman_Hall",
      "filename": "./hall_databases/Muktijoddha_Ziaur_Rahman_Hall.json",
      "totalVoters": 1749,
      "prefix": "িজয়া",
      "totalDepartments": 54
    },
    {
      "hallName": "জাতির জনক বঙ্গবন্ধু শেখ মুজিবুর রহমান হল",
      "englishName": "Bangabandhu_Sheikh_Mujibur_Rahman_Hall",
      "filename": "./hall_databases/Bangabandhu_Sheikh_Mujibur_Rahman_Hall.json",
      "totalVoters": 1609,
      "prefix": "বব",
      "totalDepartments": 56
    },
    {
      "hallName": "সূর্যসেন হল",
      "englishName": "Surya_Sen_Hall",
      "filename": "./hall_databases/Surya_Sen_Hall.json",
      "totalVoters": 1501,
      "prefix": "সয",
      "totalDepartments": 56
    },
    {
      "hallName": "হাজী মুহম্মদ মুহসীন হল",
      "englishName": "Haji_Muhammad_Muhsin_Hall",
      "filename": "./hall_databases/Haji_Muhammad_Muhsin_Hall.json",
      "totalVoters": 1403,
      "prefix": "মম,আহ",
      "totalDepartments": 60
    },
    {
      "hallName": "স্যার এ এফ রহমান হল",
      "englishName": "Sir_AF_Rahman_Hall",
      "filename": "./hall_databases/Sir_AF_Rahman_Hall.json",
      "totalVoters": 1377,
      "prefix": "এএ",
      "totalDepartments": 58
    },
    {
      "hallName": "কবি জসীম উদ্দীন হল",
      "englishName": "Kabi_Jasimuddin_Hall",
      "filename": "./hall_databases/Kabi_Jasimuddin_Hall.json",
      "totalVoters": 1299,
      "prefix": "জস",
      "totalDepartments": 51
    },
    {
      "hallName": "অমর একুশে হল",
      "englishName": "Amar_Ekushey_Hall",
      "filename": "./hall_databases/Amar_Ekushey_Hall.json",
      "totalVoters": 1291,
      "prefix": "এক",
      "totalDepartments": 31
    },
    {
      "hallName": "সলিমুল্লাহ মুসলিম হল",
      "englishName": "Salimullah_Muslim_Hall",
      "filename": "./hall_databases/Salimullah_Muslim_Hall.json",
      "totalVoters": 665,
      "prefix": "সল",
      "totalDepartments": 55
    }
  ],
  "files": [
    "./hall_databases/Begum_Rokeya_Hall.json",
    "./hall_databases/Kabi_Sufia_Kamal_Hall.json",
    "./hall_databases/Shamsun_Nahar_Hall.json",
    "./hall_databases/Begum_Fazilatunnesa_Mujib_Hall.json",
    "./hall_databases/Jagannath_Hall.json",
    "./hall_databases/Bangladesh_Kuwait_Maitree_Hall.json",
    "./hall_databases/Bijoy_Ekattor_Hall.json",
    "./hall_databases/Dr_Muhammad_Shahidullah_Hall.json",
    "./hall_databases/Shaheed_Sergeant_Zahurul_Haq_Hall.json",
    "./hall_databases/Fazlul_Huq_Muslim_Hall.json",
    "./hall_databases/Muktijoddha_Ziaur_Rahman_Hall.json",
    "./hall_databases/Bangabandhu_Sheikh_Mujibur_Rahman_Hall.json",
    "./hall_databases/Surya_Sen_Hall.json",
    "./hall_databases/Haji_Muhammad_Muhsin_Hall.json",
    "./hall_databases/Sir_AF_Rahman_Hall.json",
    "./hall_databases/Kabi_Jasimuddin_Hall.json",
    "./hall_databases/Amar_Ekushey_Hall.json",
    "./hall_databases/Salimullah_Muslim_Hall.json"
  ]
}